phi/__init__.py
phi/constants.py
phi/extra.py
phi/main.py
phi/scikit.py
phi/utils.py
cleanphi-0.1.0.dist-info/LICENSE
cleanphi-0.1.0.dist-info/METADATA
cleanphi-0.1.0.dist-info/WHEEL
cleanphi-0.1.0.dist-info/top_level.txt
cleanphi-0.1.0.dist-info/RECORD
