Metadata-Version: 2.1
Name: cleanphi
Version: 0.1.0
Summary: Natural language processing framework to clean sentences and texts.
Home-page: https://github.com/enginestein/Phi
Author: Arya Praneil Pritesh
Author-email: aryapraneil@gmail.com
Classifier: Programming Language :: Python :: 3
Classifier: Operating System :: OS Independent
Requires-Python: >=3.6
License-File: LICENSE
